AUTHORS.rst
CONTRIBUTING.rst
HISTORY.rst
LICENSE
MANIFEST.in
README.rst
setup.cfg
setup.py
analyzerdam/DAMFactory.py
analyzerdam/__init__.py
analyzerdam/baseDAM.py
analyzerdam/excelDAM.py
analyzerdam/excelLib.py
analyzerdam/googleDAM.py
analyzerdam/googleFinance.py
analyzerdam/hbaseDAM.py
analyzerdam/hbaseLib.py
analyzerdam/sqlDAM.py
analyzerdam/yahooDAM.py
analyzerdam/yahooFinance.py
analyzerdam.egg-info/PKG-INFO
analyzerdam.egg-info/SOURCES.txt
analyzerdam.egg-info/dependency_links.txt
analyzerdam.egg-info/not-zip-safe
analyzerdam.egg-info/top_level.txt
docs/Makefile
docs/authors.rst
docs/conf.py
docs/contributing.rst
docs/history.rst
docs/index.rst
docs/installation.rst
docs/make.bat
docs/readme.rst
docs/usage.rst
tests/__init__.py
tests/test_excel_dam.py
tests/test_excel_lib.py
tests/test_google_dam.py
tests/test_google_finance.py
tests/test_sql_dam.py
tests/test_yahoo_dam.py
tests/test_yahoo_finance.py