Metadata-Version: 1.1
Name: analyzerdam
Version: 0.1.0
Summary: Data Access Model for analyzer
Home-page: https://github.com/llazzaro/analyzerdam
Author: Leonardo Lazzaro
Author-email: lazzaroleonardo@gmail.com
License: BSD
Keywords: analyzerdam
Platform: UNKNOWN
Classifier: Development Status :: 2 - Pre-Alpha
Classifier: Intended Audience :: Developers
Classifier: License :: OSI Approved :: BSD License
Classifier: Natural Language :: English
Classifier: Programming Language :: Python :: 2
Classifier: Programming Language :: Python :: 2.6
Classifier: Programming Language :: Python :: 2.7
Classifier: Programming Language :: Python :: 3
Classifier: Programming Language :: Python :: 3.3
Classifier: Programming Language :: Python :: 3.4
